{
	"id": "SYNcpdeYrw2Y",
	"effects": [],
	"img": "/icon/magic/perception/eye-slit-pink.webp",
	"name": "CLEANSING WEAPON",
	"system": {
		"class": ["priest"],
		"description": "<p>One weapon you touch is wreathed in purifying flames. It deals an additional 1d4 damage (1d6 vs. undead) for the duration.</p>",
		"duration": { "type": "rounds", "value": "5" },
		"lost": false,
		"magicItem": false,
		"predefinedEffects": false,
		"properties": [],
		"range": "close",
		"tier": 2
	},
	"type": "Spell"
}
