{"id":"7SzdnC0Of9Yw","effects":[],"img":"/icon/magic/perception/eye-slit-pink.webp","name":"MAGIC CIRCLE","system":{"class":["wizard"],"description":"<p>You conjure a circle of runes out to near-sized cube centered on yourself and name a type of creature (for example, demons). For the spell’s duration, creatures of the chosen type cannot attack or cast a hostile spell on anyone inside the circle. The chosen creatures also can’t possess, compel, or beguile anyone inside the circle.</p>","duration":{"type":"focus","value":""},"lost":false,"magicItem":false,"predefinedEffects":false,"properties":[],"range":"near","tier":3},"type":"Spell"}